{
  "lastUpdate": "2026-06-27T20:56:19.499Z",
  "totalMatches": 12,
  "finishedMatchesCount": 8,
  "liveMatchesCount": 4,
  "upcomingMatchesCount": 0,
  "matches": [
    {
      "group": "FIFA World Cup",
      "date": "2026-06-26",
      "time": "02:00",
      "team1": "🇾 Paraguay",
      "team2": "🇦🇺 Australia",
      "homeTeam": "Paraguay",
      "awayTeam": "Australia",
      "score": "0 - 0",
      "status": "finished",
      "statusText": "✅ انتهت",
      "minute": "",
      "utcDate": "2026-06-26T02:00:00Z",
      "competition": "FIFA World Cup",
      "matchday": 3,
      "venue": "غير محدد",
      "referees": "Clément Turpin"
    },
    {
      "group": "FIFA World Cup",
      "date": "2026-06-26",
      "time": "02:00",
      "team1": "🇹🇷 Turkey",
      "team2": "🇺🇸 USA",
      "homeTeam": "Turkey",
      "awayTeam": "USA",
      "score": "3 - 2",
      "status": "finished",
      "statusText": "✅ انتهت",
      "minute": "",
      "utcDate": "2026-06-26T02:00:00Z",
      "competition": "FIFA World Cup",
      "matchday": 3,
      "venue": "غير محدد",
      "referees": "Mustapha Ghorbal"
    },
    {
      "group": "FIFA World Cup",
      "date": "2026-06-26",
      "time": "19:00",
      "team1": "🇸🇳 Senegal",
      "team2": "🇮🇶 Iraq",
      "homeTeam": "Senegal",
      "awayTeam": "Iraq",
      "score": "5 - 0",
      "status": "finished",
      "statusText": "✅ انتهت",
      "minute": "",
      "utcDate": "2026-06-26T19:00:00Z",
      "competition": "FIFA World Cup",
      "matchday": 3,
      "venue": "غير محدد",
      "referees": "Anthony Taylor"
    },
    {
      "group": "FIFA World Cup",
      "date": "2026-06-26",
      "time": "19:00",
      "team1": "🇳🇴 Norway",
      "team2": "🇫🇷 France",
      "homeTeam": "Norway",
      "awayTeam": "France",
      "score": "1 - 4",
      "status": "finished",
      "statusText": "✅ انتهت",
      "minute": "",
      "utcDate": "2026-06-26T19:00:00Z",
      "competition": "FIFA World Cup",
      "matchday": 3,
      "venue": "غير محدد",
      "referees": "Michael Oliver"
    },
    {
      "group": "FIFA World Cup",
      "date": "2026-06-27",
      "time": "00:00",
      "team1": "🇨🇻 Cape Verde",
      "team2": "🇸 Saudi Arabia",
      "homeTeam": "Cape Verde",
      "awayTeam": "Saudi Arabia",
      "score": "0 - 0",
      "status": "finished",
      "statusText": "✅ انتهت",
      "minute": "",
      "utcDate": "2026-06-27T00:00:00Z",
      "competition": "FIFA World Cup",
      "matchday": 3,
      "venue": "غير محدد",
      "referees": "François Letexier"
    },
    {
      "group": "FIFA World Cup",
      "date": "2026-06-27",
      "time": "00:00",
      "team1": "🇺🇾 Uruguay",
      "team2": "🇪🇸 Spain",
      "homeTeam": "Uruguay",
      "awayTeam": "Spain",
      "score": "0 - 1",
      "status": "finished",
      "statusText": "✅ انتهت",
      "minute": "",
      "utcDate": "2026-06-27T00:00:00Z",
      "competition": "FIFA World Cup",
      "matchday": 3,
      "venue": "غير محدد",
      "referees": "Ismail Elfath"
    },
    {
      "group": "FIFA World Cup",
      "date": "2026-06-27",
      "time": "03:00",
      "team1": "🇬 Egypt",
      "team2": "🇮 Iran",
      "homeTeam": "Egypt",
      "awayTeam": "Iran",
      "score": "1 - 1",
      "status": "finished",
      "statusText": "✅ انتهت",
      "minute": "",
      "utcDate": "2026-06-27T03:00:00Z",
      "competition": "FIFA World Cup",
      "matchday": 3,
      "venue": "غير محدد",
      "referees": "Szymon Marciniak"
    },
    {
      "group": "FIFA World Cup",
      "date": "2026-06-27",
      "time": "03:00",
      "team1": "🇳🇿 New Zealand",
      "team2": "🇧 Belgium",
      "homeTeam": "New Zealand",
      "awayTeam": "Belgium",
      "score": "1 - 5",
      "status": "finished",
      "statusText": "✅ انتهت",
      "minute": "",
      "utcDate": "2026-06-27T03:00:00Z",
      "competition": "FIFA World Cup",
      "matchday": 3,
      "venue": "غير محدد",
      "referees": "Adham Makhadmeh"
    },
    {
      "group": "FIFA World Cup",
      "date": "2026-06-27",
      "time": "21:00",
      "team1": "🇭 Croatia",
      "team2": "🇬🇭 Ghana",
      "homeTeam": "Croatia",
      "awayTeam": "Ghana",
      "score": "- : -",
      "status": "live",
      "statusText": "🔴 مباشر",
      "minute": "",
      "utcDate": "2026-06-27T21:00:00Z",
      "competition": "FIFA World Cup",
      "matchday": 3,
      "venue": "غير محدد",
      "referees": "Drew Fischer"
    },
    {
      "group": "FIFA World Cup",
      "date": "2026-06-27",
      "time": "21:00",
      "team1": "🇵🇦 Panama",
      "team2": "🏴󠁢󠁧 England",
      "homeTeam": "Panama",
      "awayTeam": "England",
      "score": "- : -",
      "status": "live",
      "statusText": "🔴 مباشر",
      "minute": "",
      "utcDate": "2026-06-27T21:00:00Z",
      "competition": "FIFA World Cup",
      "matchday": 3,
      "venue": "غير محدد",
      "referees": "Abdulrahman Al Jassim"
    },
    {
      "group": "FIFA World Cup",
      "date": "2026-06-27",
      "time": "23:30",
      "team1": "🇨 Congo DR",
      "team2": "🇺🇿 Uzbekistan",
      "homeTeam": "Congo DR",
      "awayTeam": "Uzbekistan",
      "score": "- : -",
      "status": "live",
      "statusText": "🔴 مباشر",
      "minute": "",
      "utcDate": "2026-06-27T23:30:00Z",
      "competition": "FIFA World Cup",
      "matchday": 3,
      "venue": "غير محدد",
      "referees": ""
    },
    {
      "group": "FIFA World Cup",
      "date": "2026-06-27",
      "time": "23:30",
      "team1": "🇨🇴 Colombia",
      "team2": "🇵🇹 Portugal",
      "homeTeam": "Colombia",
      "awayTeam": "Portugal",
      "score": "- : -",
      "status": "live",
      "statusText": "🔴 مباشر",
      "minute": "",
      "utcDate": "2026-06-27T23:30:00Z",
      "competition": "FIFA World Cup",
      "matchday": 3,
      "venue": "غير محدد",
      "referees": ""
    }
  ]
}