{
  "lastUpdate": "2026-07-03T04:38:06.986Z",
  "totalMatches": 6,
  "finishedMatchesCount": 3,
  "liveMatchesCount": 3,
  "upcomingMatchesCount": 0,
  "matches": [
    {
      "group": "FIFA World Cup",
      "date": "2026-07-02",
      "time": "00:00",
      "team1": "🇺🇸 USA",
      "team2": "🇧🇦 Bosnia-H.",
      "homeTeam": "USA",
      "awayTeam": "Bosnia-H.",
      "score": "2 - 0",
      "status": "finished",
      "statusText": "✅ انتهت",
      "minute": "",
      "utcDate": "2026-07-02T00:00:00Z",
      "competition": "FIFA World Cup",
      "matchday": null,
      "venue": "غير محدد",
      "referees": "Raphael Claus"
    },
    {
      "group": "FIFA World Cup",
      "date": "2026-07-02",
      "time": "19:00",
      "team1": "🇪🇸 Spain",
      "team2": "🇹 Austria",
      "homeTeam": "Spain",
      "awayTeam": "Austria",
      "score": "3 - 0",
      "status": "finished",
      "statusText": "✅ انتهت",
      "minute": "",
      "utcDate": "2026-07-02T19:00:00Z",
      "competition": "FIFA World Cup",
      "matchday": null,
      "venue": "غير محدد",
      "referees": "Glenn Nyberg"
    },
    {
      "group": "FIFA World Cup",
      "date": "2026-07-02",
      "time": "23:00",
      "team1": "🇵🇹 Portugal",
      "team2": "🇭 Croatia",
      "homeTeam": "Portugal",
      "awayTeam": "Croatia",
      "score": "2 - 1",
      "status": "finished",
      "statusText": "✅ انتهت",
      "minute": "",
      "utcDate": "2026-07-02T23:00:00Z",
      "competition": "FIFA World Cup",
      "matchday": null,
      "venue": "غير محدد",
      "referees": "Espen Eskås"
    },
    {
      "group": "FIFA World Cup",
      "date": "2026-07-03",
      "time": "03:00",
      "team1": "🇨 Switzerland",
      "team2": "🇩🇿 Algeria",
      "homeTeam": "Switzerland",
      "awayTeam": "Algeria",
      "score": "2 - 0",
      "status": "live",
      "statusText": "🔴 مباشر",
      "minute": "",
      "utcDate": "2026-07-03T03:00:00Z",
      "competition": "FIFA World Cup",
      "matchday": null,
      "venue": "غير محدد",
      "referees": "Yael Falcón"
    },
    {
      "group": "FIFA World Cup",
      "date": "2026-07-03",
      "time": "18:00",
      "team1": "🇦🇺 Australia",
      "team2": "🇬 Egypt",
      "homeTeam": "Australia",
      "awayTeam": "Egypt",
      "score": "- : -",
      "status": "live",
      "statusText": "🔴 مباشر",
      "minute": "",
      "utcDate": "2026-07-03T18:00:00Z",
      "competition": "FIFA World Cup",
      "matchday": null,
      "venue": "غير محدد",
      "referees": ""
    },
    {
      "group": "FIFA World Cup",
      "date": "2026-07-03",
      "time": "22:00",
      "team1": "🇦🇷 Argentina",
      "team2": "🇨🇻 Cape Verde",
      "homeTeam": "Argentina",
      "awayTeam": "Cape Verde",
      "score": "- : -",
      "status": "live",
      "statusText": "🔴 مباشر",
      "minute": "",
      "utcDate": "2026-07-03T22:00:00Z",
      "competition": "FIFA World Cup",
      "matchday": null,
      "venue": "غير محدد",
      "referees": ""
    }
  ]
}